vidua/__init__.py
vidua/__main__.py
vidua/bps.py
vidua/ips.py
vidua/py.typed
vidua/scripts.py
vidua/util.py
vidua-0.4.5.dist-info/COPYING
vidua-0.4.5.dist-info/METADATA
vidua-0.4.5.dist-info/WHEEL
vidua-0.4.5.dist-info/entry_points.txt
vidua-0.4.5.dist-info/top_level.txt
vidua-0.4.5.dist-info/zip-safe
vidua-0.4.5.dist-info/RECORD
