Metadata-Version: 2.1
Name: vidua
Version: 0.4.5
Summary: Apply patches to ROMs and other files
Home-page: http://github.com/sopoforic/vidua
Author: Tracy Poff
Author-email: tracy.poff@gmail.com
Project-URL: Documentation, https://vidua.readthedocs.io/
Project-URL: Issues, https://github.com/sopoforic/vidua/issues
Classifier: Development Status :: 3 - Alpha
Classifier: License :: OSI Approved :: GNU General Public License v3 or later (GPLv3+)
Classifier: Operating System :: OS Independent
Classifier: Programming Language :: Python :: 3
Classifier: Topic :: Utilities
License-File: COPYING
